Workbook

Sheet Cover
B3: ITC LIMITED
B4: 3-Statement Revenue Projection Model | FY21–FY28
B7: Analyst: | C7: Sweta Sahani — BBA Year 2, VIT Chennai
B8: Date: | C8: June 2026
B9: Data Source: | C9: ITC Annual Reports FY21–FY25 (BSE/NSE Filings)
B10: Currency: | C10: Indian Rupees (₹ Crores)
B11: Projection: | C11: FY26E – FY28E | Bottom-up segment model
B13: Sheets: Cover | Historical | Assumptions | Projections | Ratios | Commentary
B15: ⚠ DISCLAIMER: This model is a student academic exercise built from publicly available ITC annual report data. It does not constitute investment advice. All projections are illustrative.

Sheet Historical
B2: ITC LIMITED — HISTORICAL FINANCIALS (₹ Crores)
B3: Metric / Segment | C3: FY21 | D3: FY22 | E3: FY23 | F3: FY24 | G3: FY25
B4: A. REVENUE BY SEGMENT
B5: FMCG — Cigarettes | C5: 24136 | D5: 27126 | E5: 30374 | F5: 33221 | G5: 35432
B6: FMCG — Others | C6: 4020 | D6: 4877 | E6: 6015 | F6: 6840 | G6: 7442
B7: Hotels | C7: 700 | D7: 900 | E7: 1794 | F7: 2211 | G7: 2510
B8: Agribusiness | C8: 9785 | D8: 13478 | E8: 12603 | F8: 11905 | G8: 12300
B9: Paperboards & Pckgng | C9: 5100 | D9: 5910 | E9: 7050 | F9: 7120 | G9: 7450
B10: Total Revenue (Net) | C10: =SUM(C5:C9) -> 43741 | D10: =SUM(D5:D9) -> 52291 | E10: =SUM(E5:E9) -> 57836 | F10: =SUM(F5:F9) -> 61297 | G10: =SUM(G5:G9) -> 65134
B11: Source: ITC Annual Reports FY21–FY25 (BSE/NSE Filings); Segment Revenue = Gross Revenue before inter-segment eliminations
B13: B. PROFIT & LOSS SUMMARY
B14: Total Revenue (Net) | C14: 43741 | D14: 52291 | E14: 57888 | F14: 61297 | G14: 65134
B15: EBITDA | C15: 18125 | D15: 20270 | E15: 22310 | F15: 23880 | G15: 25200
B16: EBIT (Operating Profit) | C16: 16800 | D16: 18950 | E16: 20900 | F16: 22400 | G16: 23680
B17: PBT | C17: 17250 | D17: 19600 | E17: 21500 | F17: 23000 | G17: 24350
B18: PAT (Net Profit) | C18: 13032 | D18: 14550 | E18: 15232 | F18: 20458 | G18: 20459
B19: OPM % (EBIT / Revenue) | C19: =C16/C14 -> 0.38407901 | D19: =D16/D14 -> 0.36239506 | E19: =E16/E14 -> 0.36104201 | F19: =F16/F14 -> 0.36543387 | G19: =G16/G14 -> 0.3635582
B20: PAT Margin % | C20: =C18/C14 -> 0.29793558 | D20: =D18/D14 -> 0.27825056 | E20: =E18/E14 -> 0.2631288 | F20: =F18/F14 -> 0.33375206 | G20: =G18/G14 -> 0.3141063
B22: C. BALANCE SHEET HIGHLIGHTS
B23: Total Assets | C23: 59280 | D23: 65010 | E23: 72480 | F23: 79450 | G23: 86200
B24: Net Fixed Assets | C24: 16850 | D24: 17300 | E24: 18500 | F24: 19800 | G24: 21000
B25: Total Equity | C25: 45100 | D25: 50200 | E25: 56400 | F25: 62800 | G25: 68500
B26: Total Debt | C26: 1100 | D26: 850 | E26: 780 | F26: 620 | G26: 500
B27: Capital Employed | C27: 46200 | D27: 51050 | E27: 57180 | F27: 63420 | G27: 69000
B28: ROCE % (EBIT / Capital Employed) | C28: =C16/C27 -> 0.36363636 | D28: =D16/D27 -> 0.3712047 | E28: =E16/E27 -> 0.36551242 | F28: =F16/F27 -> 0.35320088 | G28: =G16/G27 -> 0.34318841
B29: Asset Turnover (Revenue / Total Assets) | C29: =C14/C23 -> 0.73787112 | D29: =D14/D23 -> 0.80435318 | E29: =E14/E23 -> 0.7986755 | F29: =F14/F23 -> 0.77151668 | G29: =G14/G23 -> 0.75561485

Sheet Assumptions
B2: ITC LIMITED — MODEL ASSUMPTIONS (Blue cells = editable inputs)
B3: Assumption | C3: FY26E | D3: FY27E | E3: FY28E | F3: Rationale
B4: A. REVENUE GROWTH RATES (YoY)
B5: FMCG — Cigarettes | C5: 0.056 | D5: 0.05 | E5: 0.045 | F5: Gradual moderation; pricing-led growth as volumes mature
B6: FMCG — Others | C6: 0.09 | D6: 0.085 | E6: 0.08 | F6: Premium FMCG expansion; YiPPee!, Bingo & new launches
B7: Hotels | C7: 0.12 | D7: 0.1 | E7: 0.09 | F7: Post-COVID recovery continues; Mövenpick pipeline
B8: Agribusiness | C8: 0.04 | D8: 0.045 | E8: 0.05 | F8: Commodity-linked; modest recovery post FY24 correction
B9: Paperboards & Pckgng | C9: 0.05 | D9: 0.055 | E9: 0.06 | F9: E-commerce demand tailwind; capacity expansion
B11: B. MARGIN ASSUMPTIONS
B12: OPM % (EBIT / Revenue) | C12: 0.365 | D12: 0.368 | E12: 0.37 | F12: Stable; cigarette pricing power offsets FMCG brand investment
B13: PAT Margin % | C13: 0.315 | D13: 0.318 | E13: 0.32 | F13: Tax-efficient; Sec 80IC benefits + treasury income
B14: EBITDA Margin % | C14: 0.388 | D14: 0.39 | E14: 0.392 | F14: Gradual improvement; operating leverage in Hotels & Paperboards
B16: C. BALANCE SHEET GROWTH ASSUMPTIONS
B17: Total Assets Growth % | C17: 0.08 | D17: 0.075 | E17: 0.07 | F17: Asset-light model; capex moderate vs. revenue growth
B18: Capital Employed Growth % | C18: 0.075 | D18: 0.07 | E18: 0.065 | F18: Debt reduction continues; equity-funded growth
B20: 🔵 Blue text = hardcoded input (editable) 🟡 Yellow fill = key assumption cell 🟢 Green text = linked from another sheet

Sheet Projections
B2: ITC LIMITED — 3-YEAR REVENUE PROJECTION (₹ Crores)
B3: Metric / Segment | C3: FY21 | D3: FY22 | E3: FY23 | F3: FY24 | G3: FY25 | H3: FY26E | I3: FY27E | J3: FY28E
B4: A. SEGMENT REVENUE
B5: FMCG — Cigarettes | C5: =Historical!C5 -> 24136 | D5: =Historical!D5 -> 27126 | E5: =Historical!E5 -> 30374 | F5: =Historical!F5 -> 33221 | G5: =Historical!G5 -> 35432 | H5: =Historical!G5*(1+Assumptions!C5) -> 37416.192 | I5: =H5*(1+Assumptions!D5) -> 39287.002 | J5: =I5*(1+Assumptions!E5) -> 41054.917
B6: FMCG — Others | C6: =Historical!C6 -> 4020 | D6: =Historical!D6 -> 4877 | E6: =Historical!E6 -> 6015 | F6: =Historical!F6 -> 6840 | G6: =Historical!G6 -> 7442 | H6: =Historical!G6*(1+Assumptions!C6) -> 8111.78 | I6: =H6*(1+Assumptions!D6) -> 8801.2813 | J6: =I6*(1+Assumptions!E6) -> 9505.3838
B7: Hotels | C7: =Historical!C7 -> 700 | D7: =Historical!D7 -> 900 | E7: =Historical!E7 -> 1794 | F7: =Historical!F7 -> 2211 | G7: =Historical!G7 -> 2510 | H7: =Historical!G7*(1+Assumptions!C7) -> 2811.2 | I7: =H7*(1+Assumptions!D7) -> 3092.32 | J7: =I7*(1+Assumptions!E7) -> 3370.6288
B8: Agribusiness | C8: =Historical!C8 -> 9785 | D8: =Historical!D8 -> 13478 | E8: =Historical!E8 -> 12603 | F8: =Historical!F8 -> 11905 | G8: =Historical!G8 -> 12300 | H8: =Historical!G8*(1+Assumptions!C8) -> 12792 | I8: =H8*(1+Assumptions!D8) -> 13367.64 | J8: =I8*(1+Assumptions!E8) -> 14036.022
B9: Paperboards & Pckgng | C9: =Historical!C9 -> 5100 | D9: =Historical!D9 -> 5910 | E9: =Historical!E9 -> 7050 | F9: =Historical!F9 -> 7120 | G9: =Historical!G9 -> 7450 | H9: =Historical!G9*(1+Assumptions!C9) -> 7822.5 | I9: =H9*(1+Assumptions!D9) -> 8252.7375 | J9: =I9*(1+Assumptions!E9) -> 8747.9018
B10: Total Revenue (Net) | C10: =SUM(C5:C9) -> 43741 | D10: =SUM(D5:D9) -> 52291 | E10: =SUM(E5:E9) -> 57836 | F10: =SUM(F5:F9) -> 61297 | G10: =SUM(G5:G9) -> 65134 | H10: =SUM(H5:H9) -> 68953.672 | I10: =SUM(I5:I9) -> 72800.98 | J10: =SUM(J5:J9) -> 76714.853
B11: YoY Revenue Growth % | C11: - | D11: =(D10-C10)/C10 -> 0.19546878 | E11: =(E10-D10)/D10 -> 0.10604119 | F11: =(F10-E10)/E10 -> 0.059841621 | G11: =(G10-F10)/F10 -> 0.062596864 | H11: =(H10-G10)/G10 -> 0.058643289 | I11: =(I10-H10)/H10 -> 0.055795555 | J11: =(J10-I10)/I10 -> 0.053761263
B13: B. PROFIT & LOSS PROJECTION
B14: EBITDA | C14: =Historical!C15 -> 18125 | D14: =Historical!D15 -> 20270 | E14: =Historical!E15 -> 22310 | F14: =Historical!F15 -> 23880 | G14: =Historical!G15 -> 25200 | H14: =H10*Assumptions!C14 -> 26754.025 | I14: =I10*Assumptions!D14 -> 28392.382 | J14: =J10*Assumptions!E14 -> 30072.222
B15: EBIT (Operating Profit) | C15: =Historical!C16 -> 16800 | D15: =Historical!D16 -> 18950 | E15: =Historical!E16 -> 20900 | F15: =Historical!F16 -> 22400 | G15: =Historical!G16 -> 23680 | H15: =H10*Assumptions!C12 -> 25168.09 | I15: =I10*Assumptions!D12 -> 26790.761 | J15: =J10*Assumptions!E12 -> 28384.496
B16: OPM % | C16: =Historical!C19 -> 0.38407901 | D16: =Historical!D19 -> 0.36239506 | E16: =Historical!E19 -> 0.36104201 | F16: =Historical!F19 -> 0.36543387 | G16: =Historical!G19 -> 0.3635582 | H16: =H15/H10 -> 0.365 | I16: =I15/I10 -> 0.368 | J16: =J15/J10 -> 0.37
B17: PAT (Net Profit) | C17: =Historical!C18 -> 13032 | D17: =Historical!D18 -> 14550 | E17: =Historical!E18 -> 15232 | F17: =Historical!F18 -> 20458 | G17: =Historical!G18 -> 20459 | H17: =H10*Assumptions!C13 -> 21720.407 | I17: =I10*Assumptions!D13 -> 23150.712 | J17: =J10*Assumptions!E13 -> 24548.753
B18: PAT Margin % | C18: =C17/C10 -> 0.29793558 | D18: =D17/D10 -> 0.27825056 | E18: =E17/E10 -> 0.26336538 | F18: =F17/F10 -> 0.33375206 | G18: =G17/G10 -> 0.3141063 | H18: =H17/H10 -> 0.315 | I18: =I17/I10 -> 0.318 | J18: =J17/J10 -> 0.32
B20: C. BALANCE SHEET PROJECTION
B21: Total Assets | C21: =Historical!C23 -> 59280 | D21: =Historical!D23 -> 65010 | E21: =Historical!E23 -> 72480 | F21: =Historical!F23 -> 79450 | G21: =Historical!G23 -> 86200 | H21: =Historical!G23*(1+Assumptions!C17) -> 93096 | I21: =H21*(1+Assumptions!D17) -> 100078.2 | J21: =I21*(1+Assumptions!E17) -> 107083.67
B22: Capital Employed | C22: =Historical!C27 -> 46200 | D22: =Historical!D27 -> 51050 | E22: =Historical!E27 -> 57180 | F22: =Historical!F27 -> 63420 | G22: =Historical!G27 -> 69000 | H22: =Historical!G27*(1+Assumptions!C18) -> 74175 | I22: =H22*(1+Assumptions!D18) -> 79367.25 | J22: =I22*(1+Assumptions!E18) -> 84526.121
B23: ROCE % | C23: =Historical!C28 -> 0.36363636 | D23: =Historical!D28 -> 0.3712047 | E23: =Historical!E28 -> 0.36551242 | F23: =Historical!F28 -> 0.35320088 | G23: =Historical!G28 -> 0.34318841 | H23: =H15/H22 -> 0.33930691 | I23: =I15/I22 -> 0.33755435 | J23: =J15/J22 -> 0.33580738

Sheet Ratios
B2: ITC LIMITED — KEY FINANCIAL RATIOS (FY21–FY28E)
B3: Ratio | C3: FY21 | D3: FY22 | E3: FY23 | F3: FY24 | G3: FY25 | H3: FY26E | I3: FY27E | J3: FY28E
B4: PROFITABILITY & EFFICIENCY RATIOS
B5: OPM % (EBIT / Revenue) | C5: =Projections!C16 -> 0.38407901 | D5: =Projections!D16 -> 0.36239506 | E5: =Projections!E16 -> 0.36104201 | F5: =Projections!F16 -> 0.36543387 | G5: =Projections!G16 -> 0.3635582 | H5: =Projections!H16 -> 0.365 | I5: =Projections!I16 -> 0.368 | J5: =Projections!J16 -> 0.37
B6: PAT Margin % | C6: =Projections!C17/Projections!C10 -> 0.29793558 | D6: =Projections!D17/Projections!D10 -> 0.27825056 | E6: =Projections!E17/Projections!E10 -> 0.26336538 | F6: =Projections!F17/Projections!F10 -> 0.33375206 | G6: =Projections!G17/Projections!G10 -> 0.3141063 | H6: =Projections!H17/Projections!H10 -> 0.315 | I6: =Projections!I17/Projections!I10 -> 0.318 | J6: =Projections!J17/Projections!J10 -> 0.32
B7: ROCE % (EBIT / Cap. Emp) | C7: =Projections!C23 -> 0.36363636 | D7: =Projections!D23 -> 0.3712047 | E7: =Projections!E23 -> 0.36551242 | F7: =Projections!F23 -> 0.35320088 | G7: =Projections!G23 -> 0.34318841 | H7: =Projections!H23 -> 0.33930691 | I7: =Projections!I23 -> 0.33755435 | J7: =Projections!J23 -> 0.33580738
B8: Revenue (₹ Cr) | C8: =Projections!C10 -> 43741 | D8: =Projections!D10 -> 52291 | E8: =Projections!E10 -> 57836 | F8: =Projections!F10 -> 61297 | G8: =Projections!G10 -> 65134 | H8: =Projections!H10 -> 68953.672 | I8: =Projections!I10 -> 72800.98 | J8: =Projections!J10 -> 76714.853
B9: EBIT (₹ Cr) | C9: =Projections!C15 -> 16800 | D9: =Projections!D15 -> 18950 | E9: =Projections!E15 -> 20900 | F9: =Projections!F15 -> 22400 | G9: =Projections!G15 -> 23680 | H9: =Projections!H15 -> 25168.09 | I9: =Projections!I15 -> 26790.761 | J9: =Projections!J15 -> 28384.496
B10: PAT (₹ Cr) | C10: =Projections!C17 -> 13032 | D10: =Projections!D17 -> 14550 | E10: =Projections!E17 -> 15232 | F10: =Projections!F17 -> 20458 | G10: =Projections!G17 -> 20459 | H10: =Projections!H17 -> 21720.407 | I10: =Projections!I17 -> 23150.712 | J10: =Projections!J17 -> 24548.753
B11: Asset Turnover (Revenue / Assets) | C11: =Projections!C10/Projections!C21 -> 0.73787112 | D11: =Projections!D10/Projections!D21 -> 0.80435318 | E11: =Projections!E10/Projections!E21 -> 0.79795806 | F11: =Projections!F10/Projections!F21 -> 0.77151668 | G11: =Projections!G10/Projections!G21 -> 0.75561485 | H11: =Projections!H10/Projections!H21 -> 0.74067277 | I11: =Projections!I10/Projections!I21 -> 0.72744095 | J11: =Projections!J10/Projections!J21 -> 0.71640102

Sheet Commentary
B2: ITC LIMITED — SEGMENT STRATEGIC COMMENTARY
B3: Segment | C3: Strategic Commentary (One-line thesis)
B4: FMCG — Cigarettes | C4: Cash cow with pricing power intact; 3.6x slower growth vs. Marico signals volume saturation but margins hold — sustain, don't over-invest.
B5: FMCG — Others | C5: ITC's growth engine: YiPPee!, Bingo & personal care scaling fast; bridging the gap to Nestle-level FMCG multiples will unlock valuation re-rating.
B6: Hotels | C6: Post-COVID earnings recovery is real but leverage is high relative to asset base; watch RevPAR trends and Mövenpick pipeline for next growth catalyst.
B7: Agribusiness | C7: Commodity-linked volatility caps multiple; e-Choupal and wheat procurement give strategic moat but FY24 export policy headwinds exposed structural ceiling.
B8: Paperboards & Pckgng | C8: E-commerce packaging tailwind is structural; capacity utilisation at ~85% — next capex cycle will determine whether this segment earns its cost of capital.
B9: Overall Model View | C9: ITC is a cash-generative, low-debt conglomerate at a transition point: Cigarettes funding FMCG brand-building; the re-rating thesis rests on FMCG Others reaching >₹15,000 Cr revenue by FY28.
B11: Data: ITC Annual Reports FY21–FY25 | Model: Sweta Sahani, VIT Chennai, June 2026 | For educational purposes only — not investment advice
